photon_observer/__init__.py
photon_observer/base_photon_command.py
photon_observer/enums.py
photon_observer/fragment_buffer.py
photon_observer/photon_command.py
photon_observer/reliable_fragment.py
photon_observer/reliable_message.py
photon_observer-0.1.dist-info/LICENSE
photon_observer-0.1.dist-info/METADATA
photon_observer-0.1.dist-info/WHEEL
photon_observer-0.1.dist-info/top_level.txt
photon_observer-0.1.dist-info/RECORD
