Metadata-Version: 2.1
Name: photon-observer
Version: 0.1
Summary: Tools for working with the Photon protocol
Home-page: https://github.com/MyrikLD/photon_observer
Author: Yorsh Sergey
Author-email: myrik260138@gmail.com
License: MIT
Keywords: photon binary protocol
Classifier: Development Status :: 3 - Alpha
Classifier: Intended Audience :: Developers
Classifier: Topic :: Software Development :: Libraries
Classifier: Programming Language :: Python :: 3
Classifier: Programming Language :: Python :: 3.8
Classifier: Programming Language :: Python :: 3.9
Classifier: Programming Language :: Python :: 3.10
Classifier: Programming Language :: Python :: 3.11
Classifier: Programming Language :: Python :: 3.12
Provides-Extra: test
License-File: LICENSE
